tasks.py
dalm/__init__.py
dalm/cli.py
dalm/utils.py
dalm/datasets/__init__.py
dalm/datasets/docs_to_passage/__init__.py
dalm/datasets/docs_to_passage/json_pre_process.py
dalm/datasets/docs_to_passage/main.py
dalm/datasets/docs_to_passage/utils.py
dalm/datasets/qa_gen/__init__.py
dalm/datasets/qa_gen/question_answer_generation.py
dalm/eval/__init__.py
dalm/eval/eval_rag.py
dalm/eval/eval_retriever_only.py
dalm/eval/utils.py
dalm/models/__init__.py
dalm/models/rag_e2e_base_model.py
dalm/models/retriever_only_base_model.py
dalm/training/__init__.py
dalm/training/rag_e2e/__init__.py
dalm/training/rag_e2e/train_rage2e.py
dalm/training/retriever_only/__init__.py
dalm/training/retriever_only/train_retriever_only.py
dalm/training/utils/__init__.py
dalm/training/utils/rag_e2e_dataloader_utils.py
dalm/training/utils/retriever_only_dataloader_utils.py
dalm/training/utils/train_utils.py
experiments/llama-index-10k/data_gen.py
experiments/llama-index-synthetic-data/eval_utils.py
experiments/llama-index-synthetic-data/evaluate_llama_model.py
experiments/llama-index-synthetic-data/prepare_data_for_llama.py
experiments/llama-index-synthetic-data/train_dataset_llama.py
indomain-0.0.5.dist-info/METADATA
indomain-0.0.5.dist-info/WHEEL
indomain-0.0.5.dist-info/entry_points.txt
indomain-0.0.5.dist-info/licenses/LICENSE
indomain-0.0.5.dist-info/RECORD
