Metadata-Version: 2.1
Name: indomain
Version: 0.0.5
Project-URL: Home, https://arcee.ai
Author-email: Shamane Siri <shamane@arcee.ai>, Ben Epstein <ben@arcee.ai>
License: Apache 2.0
License-File: LICENSE
Requires-Python: >=3.10
Requires-Dist: accelerate
Requires-Dist: bitsandbytes
Requires-Dist: datasets
Requires-Dist: diffusers
Requires-Dist: evaluate
Requires-Dist: hnswlib
Requires-Dist: peft
Requires-Dist: scikit-learn
Requires-Dist: torch
Requires-Dist: tqdm
Requires-Dist: transformers
Requires-Dist: typer
Provides-Extra: dev
Requires-Dist: black; extra == 'dev'
Requires-Dist: boto3-stubs; extra == 'dev'
Requires-Dist: build; extra == 'dev'
Requires-Dist: httpx; extra == 'dev'
Requires-Dist: invoke; extra == 'dev'
Requires-Dist: jupyter; extra == 'dev'
Requires-Dist: mypy; extra == 'dev'
Requires-Dist: packaging; extra == 'dev'
Requires-Dist: pandas-stubs; extra == 'dev'
Requires-Dist: pre-commit; extra == 'dev'
Requires-Dist: pytest; extra == 'dev'
Requires-Dist: pytest-cov; extra == 'dev'
Requires-Dist: pytest-mock; extra == 'dev'
Requires-Dist: pytest-timeout; extra == 'dev'
Requires-Dist: python-dotenv; extra == 'dev'
Requires-Dist: rich; extra == 'dev'
Requires-Dist: ruff; extra == 'dev'
Requires-Dist: types-cachetools; extra == 'dev'
Requires-Dist: types-markdown; extra == 'dev'
Requires-Dist: types-pyyaml; extra == 'dev'
Requires-Dist: types-requests; extra == 'dev'
Requires-Dist: types-tqdm; extra == 'dev'
